[
  {
    "id": 1,
    "slug": "dyn_hong_bang",
    "name": "Thời Hồng Bàng (Hùng Vương)",
    "year_range": "2879 TCN - 258 TCN",
    "start_year": -2879,
    "end_year": -258,
    "summary": "Thời kỳ huyền sử gắn liền với các Vua Hùng dựng nước Văn Lang, đặt nền móng sơ khai cho quốc gia.",
    "agent_id": "agent_hong_bang",
    "color": "#A52A2A",
    "notable_figures": [
      "Kinh Dương Vương",
      "Lạc Long Quân",
      "Hùng Vương"
    ],
    "key_events": [
      "Truyền thuyết Lạc Long Quân - Âu Cơ",
      "Thành lập nhà nước Văn Lang"
    ]
  },
  {
    "id": 2,
    "slug": "dyn_thuc",
    "name": "Nhà Thục (An Dương Vương)",
    "year_range": "257 TCN - 179 TCN",
    "start_year": -257,
    "end_year": -179,
    "summary": "An Dương Vương thống nhất Âu Việt và Lạc Việt, lập nước Âu Lạc, xây thành Cổ Loa và chế tạo nỏ thần.",
    "agent_id": "agent_thuc",
    "color": "#8B4513",
    "notable_figures": [
      "An Dương Vương (Thục Phán)"
    ],
    "key_events": [
      "Thống nhất Âu Việt - Lạc Việt",
      "Xây thành Cổ Loa",
      "Thất thủ trước Triệu Đà"
    ]
  },
  {
    "id": 3,
    "slug": "dyn_trieu",
    "name": "Nhà Triệu (Nam Việt)",
    "year_range": "207 TCN - 111 TCN",
    "start_year": -207,
    "end_year": -111,
    "summary": "Triệu Đà lập nước Nam Việt, mở rộng lãnh thổ và cai trị độc lập với nhà Hán trước khi bị sáp nhập.",
    "agent_id": "agent_trieu",
    "color": "#D2691E",
    "notable_figures": [
      "Triệu Đà (Triệu Vũ Đế)",
      "Triệu Mạt (Triệu Văn Đế)"
    ],
    "key_events": [
      "Thành lập nước Nam Việt",
      "Bị nhà Hán thôn tính (111 TCN)"
    ]
  },
  {
    "id": 4,
    "slug": "period_bac_thuoc_1",
    "name": "Thời Bắc thuộc lần 1",
    "year_range": "111 TCN - 40",
    "start_year": -111,
    "end_year": 40,
    "summary": "Giai đoạn Việt Nam bị nhà Hán đô hộ, bắt đầu quá trình Hán hóa nhưng cũng nhen nhóm các cuộc khởi nghĩa.",
    "agent_id": "agent_bac_thuoc_1",
    "color": "#808080",
    "notable_figures": [
      "Tích Quang",
      "Nhâm Diên"
    ],
    "key_events": [
      "Nhà Hán sáp nhập Nam Việt",
      "Chính sách đồng hóa"
    ]
  },
  {
    "id": 5,
    "slug": "dyn_trung_vuong",
    "name": "Trưng Vương",
    "year_range": "40 - 43",
    "start_year": 40,
    "end_year": 43,
    "summary": "Hai Bà Trưng lãnh đạo khởi nghĩa chống nhà Đông Hán, giành độc lập trong 3 năm.",
    "agent_id": "agent_trung_vuong",
    "color": "#FFD700",
    "notable_figures": [
      "Trưng Trắc",
      "Trưng Nhị"
    ],
    "key_events": [
      "Khởi nghĩa Hai Bà Trưng (40)",
      "Bị Mã Viện đàn áp (43)"
    ]
  },
  {
    "id": 6,
    "slug": "period_bac_thuoc_2",
    "name": "Thời Bắc thuộc lần 2",
    "year_range": "43 - 544",
    "start_year": 43,
    "end_year": 544,
    "summary": "Giai đoạn đô hộ kéo dài của Đông Hán, Ngô, Tấn, Tống, Tề, Lương với nhiều cuộc khởi nghĩa.",
    "agent_id": "agent_bac_thuoc_2",
    "color": "#696969",
    "notable_figures": [
      "Sĩ Nhiếp",
      "Bà Triệu (Triệu Thị Trinh)"
    ],
    "key_events": [
      "Khởi nghĩa Bà Triệu (248)"
    ]
  },
  {
    "id": 7,
    "slug": "dyn_tien_ly",
    "name": "Nhà Tiền Lý (Vạn Xuân)",
    "year_range": "544 - 602",
    "start_year": 544,
    "end_year": 602,
    "summary": "Lý Nam Đế khởi nghĩa, lập nước Vạn Xuân, khẳng định chủ quyền độc lập.",
    "agent_id": "agent_tien_ly",
    "color": "#4682B4",
    "notable_figures": [
      "Lý Nam Đế (Lý Bí)",
      "Triệu Quang Phục",
      "Lý Phật Tử"
    ],
    "key_events": [
      "Khởi nghĩa Lý Bí (542)",
      "Thành lập nước Vạn Xuân (544)",
      "Bị nhà Tùy xâm lược (602)"
    ]
  },
  {
    "id": 8,
    "slug": "period_bac_thuoc_3",
    "name": "Thời Bắc thuộc lần 3",
    "year_range": "602 - 905",
    "start_year": 602,
    "end_year": 905,
    "summary": "Giai đoạn bị nhà Tùy và nhà Đường đô hộ (An Nam đô hộ phủ). Văn hóa Đường ảnh hưởng sâu rộng.",
    "agent_id": "agent_bac_thuoc_3",
    "color": "#708090",
    "notable_figures": [
      "Mai Thúc Loan",
      "Phùng Hưng",
      "Cao Biền"
    ],
    "key_events": [
      "Khởi nghĩa Mai Thúc Loan (713-722)",
      "Khởi nghĩa Phùng Hưng (776-791)"
    ]
  },
  {
    "id": 9,
    "slug": "period_tu_chu",
    "name": "Thời Tự chủ (Họ Khúc, Họ Dương)",
    "year_range": "905 - 938",
    "start_year": 905,
    "end_year": 938,
    "summary": "Giai đoạn chuyển tiếp, Họ Khúc và Họ Dương giành quyền tự chủ từ nhà Đường, đặt nền móng cho độc lập.",
    "agent_id": "agent_tu_chu",
    "color": "#BDB76B",
    "notable_figures": [
      "Khúc Thừa Dụ",
      "Khúc Hạo",
      "Dương Đình Nghệ"
    ],
    "key_events": [
      "Khúc Thừa Dụ giành quyền Tiết độ sứ (905)"
    ]
  },
  {
    "id": 10,
    "slug": "dyn_ngo",
    "name": "Nhà Ngô",
    "year_range": "939 - 965",
    "start_year": 939,
    "end_year": 965,
    "summary": "Ngô Quyền đánh bại quân Nam Hán trên sông Bạch Đằng, chấm dứt 1000 năm Bắc thuộc, mở ra kỷ nguyên độc lập.",
    "agent_id": "agent_ngo",
    "color": "#556B2F",
    "notable_figures": [
      "Ngô Quyền",
      "Dương Tam Kha",
      "Ngô Xương Văn"
    ],
    "key_events": [
      "Chiến thắng Bạch Đằng (938)",
      "Xưng vương, lập kinh đô ở Cổ Loa (939)"
    ]
  },
  {
    "id": 11,
    "slug": "period_12_su_quan",
    "name": "Loạn 12 Sứ quân",
    "year_range": "966 - 968",
    "start_year": 966,
    "end_year": 968,
    "summary": "Thời kỳ hỗn loạn sau khi nhà Ngô tan rã, 12 sứ quân cát cứ các nơi, đất nước bị chia cắt.",
    "agent_id": "agent_12_su_quan",
    "color": "#A9A9A9",
    "notable_figures": [
      "Ngô Nhật Khánh",
      "Kiều Công Hãn",
      "Đỗ Cảnh Thạc"
    ],
    "key_events": [
      "Đất nước chia cắt thành 12 vùng cát cứ"
    ]
  },
  {
    "id": 12,
    "slug": "dyn_dinh",
    "name": "Nhà Đinh",
    "year_range": "968 - 980",
    "start_year": 968,
    "end_year": 980,
    "summary": "Đinh Bộ Lĩnh thống nhất 12 sứ quân, lập nước Đại Cồ Việt, đặt kinh đô tại Hoa Lư.",
    "agent_id": "agent_dinh",
    "color": "#CD853F",
    "notable_figures": [
      "Đinh Bộ Lĩnh (Đinh Tiên Hoàng)",
      "Đinh Liễn",
      "Đinh Toàn"
    ],
    "key_events": [
      "Thống nhất 12 sứ quân (968)",
      "Đặt quốc hiệu Đại Cồ Việt"
    ]
  },
  {
    "id": 13,
    "slug": "dyn_tien_le",
    "name": "Nhà Tiền Lê",
    "year_range": "980 - 1009",
    "start_year": 980,
    "end_year": 1009,
    "summary": "Lê Hoàn lên ngôi, lập ra nhà Tiền Lê, lãnh đạo kháng chiến chống Tống, phát triển kinh tế và ngoại giao.",
    "agent_id": "agent_tien_le",
    "color": "#B8860B",
    "notable_figures": [
      "Lê Hoàn (Lê Đại Hành)",
      "Lê Long Đĩnh"
    ],
    "key_events": [
      "Kháng chiến chống Tống lần thứ nhất (981)",
      "Lễ tịch điền mở mang nông nghiệp"
    ]
  },
  {
    "id": 14,
    "slug": "dyn_ly",
    "name": "Nhà Lý",
    "year_range": "1009 - 1225",
    "start_year": 1009,
    "end_year": 1225,
    "summary": "Thời kỳ xây dựng Thăng Long, phát triển Phật giáo, ban hành luật Hình thư, đặt nền móng văn hóa Đại Việt.",
    "agent_id": "agent_ly",
    "color": "#F3C94C",
    "notable_figures": [
      "Lý Công Uẩn (Lý Thái Tổ)",
      "Lý Thường Kiệt",
      "Lý Nhân Tông"
    ],
    "key_events": [
      "Chiếu dời đô về Thăng Long (1010)",
      "Kháng chiến chống Tống (1075-1077)",
      "Xây dựng Văn Miếu (1070)"
    ]
  },
  {
    "id": 15,
    "slug": "dyn_tran",
    "name": "Nhà Trần",
    "year_range": "1225 - 1400",
    "start_year": 1225,
    "end_year": 1400,
    "summary": "Thời kỳ rực rỡ với ba lần kháng chiến chống Mông-Nguyên, phát triển Nho giáo và chữ Nôm.",
    "agent_id": "agent_tran",
    "color": "#E3B341",
    "notable_figures": [
      "Trần Thái Tông",
      "Trần Hưng Đạo",
      "Trần Nhân Tông"
    ],
    "key_events": [
      "Ba lần kháng chiến chống Mông-Nguyên (1258, 1285, 1288)",
      "Hội nghị Diên Hồng",
      "Thành lập Thiền phái Trúc Lâm"
    ]
  },
  {
    "id": 16,
    "slug": "dyn_ho",
    "name": "Nhà Hồ",
    "year_range": "1400 - 1407",
    "start_year": 1400,
    "end_year": 1407,
    "summary": "Hồ Quý Ly cải cách, phát hành tiền giấy, xây thành Tây Đô nhưng thất bại trong cuộc kháng chiến chống Minh.",
    "agent_id": "agent_ho",
    "color": "#9A8B4F",
    "notable_figures": [
      "Hồ Quý Ly",
      "Hồ Hán Thương"
    ],
    "key_events": [
      "Cải cách của Hồ Quý Ly",
      "Xây thành Tây Đô",
      "Kháng chiến chống Minh thất bại (1407)"
    ]
  },
  {
    "id": 17,
    "slug": "period_bac_thuoc_4",
    "name": "Thời Bắc thuộc lần 4 (Minh thuộc)",
    "year_range": "1407 - 1427",
    "start_year": 1407,
    "end_year": 1427,
    "summary": "Giai đoạn bị nhà Minh đô hộ hà khắc với chính sách đồng hóa tàn bạo, dẫn đến nhiều cuộc khởi nghĩa.",
    "agent_id": "agent_bac_thuoc_4",
    "color": "#5E5E5E",
    "notable_figures": [
      "Trương Phụ",
      "Hoàng Phúc"
    ],
    "key_events": [
      "Nhà Minh đô hộ Đại Việt",
      "Chính sách đồng hóa, vơ vét tài nguyên"
    ]
  },
  {
    "id": 18,
    "slug": "dyn_hau_tran",
    "name": "Nhà Hậu Trần",
    "year_range": "1407 - 1413",
    "start_year": 1407,
    "end_year": 1413,
    "summary": "Nỗ lực kháng chiến chống Minh của tôn thất nhà Trần (Trần Ngỗi, Trần Quý Khoáng) nhưng không thành công.",
    "agent_id": "agent_hau_tran",
    "color": "#C0C0C0",
    "notable_figures": [
      "Trần Ngỗi (Giản Định Đế)",
      "Trần Quý Khoáng (Trùng Quang Đế)"
    ],
    "key_events": [
      "Kháng chiến chống Minh ở Nghệ An, Thanh Hóa"
    ]
  },
  {
    "id": 19,
    "slug": "dyn_hau_le_so",
    "name": "Nhà Hậu Lê (Lê Sơ)",
    "year_range": "1428 - 1527",
    "start_year": 1428,
    "end_year": 1527,
    "summary": "Lê Lợi lãnh đạo Khởi nghĩa Lam Sơn, lập ra nhà Hậu Lê. Thời kỳ thịnh trị (Hồng Đức), Nho giáo cực thịnh.",
    "agent_id": "agent_hau_le_so",
    "color": "#D4AF37",
    "notable_figures": [
      "Lê Lợi (Lê Thái Tổ)",
      "Nguyễn Trãi",
      "Lê Thánh Tông"
    ],
    "key_events": [
      "Khởi nghĩa Lam Sơn (1418-1427)",
      "Ban hành bộ luật Hồng Đức"
    ]
  },
  {
    "id": 20,
    "slug": "dyn_mac",
    "name": "Nhà Mạc (Bắc triều)",
    "year_range": "1527 - 1592",
    "start_year": 1527,
    "end_year": 1592,
    "summary": "Mạc Đăng Dung cướp ngôi nhà Lê, lập ra nhà Mạc cai trị vùng phía Bắc trong thời kỳ Nam-Bắc triều.",
    "agent_id": "agent_mac",
    "color": "#4A5D23",
    "notable_figures": [
      "Mạc Đăng Dung",
      "Mạc Đăng Doanh",
      "Mạc Kính Điển"
    ],
    "key_events": [
      "Mạc Đăng Dung giành ngôi (1527)",
      "Chiến tranh Nam-Bắc triều"
    ]
  },
  {
    "id": 21,
    "slug": "period_nam_bac_trieu",
    "name": "Nam-Bắc triều (Lê-Mạc)",
    "year_range": "1533 - 1592",
    "start_year": 1533,
    "end_year": 1592,
    "summary": "Thời kỳ phân chia: Nhà Mạc ở Thăng Long và Nhà Lê Trung hưng ở Thanh Hóa, Nghệ An.",
    "agent_id": "agent_nam_bac_trieu",
    "color": "#B22222",
    "notable_figures": [
      "Nguyễn Kim",
      "Trịnh Kiểm",
      "Mạc Kính Điển"
    ],
    "key_events": [
      "Nguyễn Kim lập Lê Trang Tông (1533)",
      "Chiến tranh Lê-Mạc"
    ]
  },
  {
    "id": 22,
    "slug": "period_trinh_nguyen",
    "name": "Trịnh-Nguyễn phân tranh",
    "year_range": "1627 - 1789",
    "start_year": 1627,
    "end_year": 1789,
    "summary": "Đất nước chia làm hai: Đàng Ngoài (Chúa Trịnh) và Đàng Trong (Chúa Nguyễn), lấy sông Gianh làm ranh giới.",
    "agent_id": "agent_trinh_nguyen",
    "color": "#DC143C",
    "notable_figures": [
      "Trịnh Tùng",
      "Nguyễn Hoàng",
      "Đào Duy Từ"
    ],
    "key_events": [
      "Bảy lần chiến tranh Trịnh-Nguyễn",
      "Phồn vinh thương mại (Phố Hiến, Hội An)"
    ]
  },
  {
    "id": 23,
    "slug": "dyn_tay_son",
    "name": "Nhà Tây Sơn",
    "year_range": "1778 - 1802",
    "start_year": 1778,
    "end_year": 1802,
    "summary": "Anh em Nguyễn Nhạc, Nguyễn Huệ, Nguyễn Lữ khởi nghĩa, lật đổ Trịnh-Nguyễn, thống nhất đất nước.",
    "agent_id": "agent_tay_son",
    "color": "#FF4500",
    "notable_figures": [
      "Nguyễn Nhạc",
      "Nguyễn Huệ (Quang Trung)",
      "Nguyễn Lữ"
    ],
    "key_events": [
      "Lật đổ Chúa Nguyễn (1777) và Chúa Trịnh (1786)",
      "Đại phá quân Xiêm (1785)",
      "Đại phá quân Thanh (1789)"
    ]
  },
  {
    "id": 24,
    "slug": "dyn_nguyen",
    "name": "Nhà Nguyễn",
    "year_range": "1802 - 1945",
    "start_year": 1802,
    "end_year": 1945,
    "summary": "Nguyễn Ánh thống nhất đất nước, lập ra nhà Nguyễn với kinh đô ở Phú Xuân. Từ giữa thế kỷ XIX, thực dân Pháp xâm lược.",
    "agent_id": "agent_nguyen",
    "color": "#DAA520",
    "notable_figures": [
      "Nguyễn Ánh (Gia Long)",
      "Minh Mạng",
      "Tự Đức",
      "Bảo Đại"
    ],
    "key_events": [
      "Thống nhất đất nước (1802)",
      "Pháp xâm lược (1858)",
      "Vua Bảo Đại thoái vị (1945)"
    ]
  },
  {
    "id": 25,
    "slug": "period_phap_thuoc",
    "name": "Thời kỳ Pháp thuộc",
    "year_range": "1884 - 1945",
    "start_year": 1884,
    "end_year": 1945,
    "summary": "Giai đoạn Việt Nam là thuộc địa của Pháp (Liên bang Đông Dương), xã hội và kinh tế thay đổi sâu sắc.",
    "agent_id": "agent_phap_thuoc",
    "color": "#00008B",
    "notable_figures": [
      "Phan Bội Châu",
      "Phan Châu Trinh",
      "Hoàng Hoa Thám"
    ],
    "key_events": [
      "Hòa ước Patenôtre (1884)",
      "Phong trào Cần Vương",
      "Phong trào Đông Du"
    ]
  },
  {
    "id": 26,
    "slug": "period_hien_dai_chia_cat",
    "name": "Thời kỳ Hiện đại (1945-1975)",
    "year_range": "1945 - 1975",
    "start_year": 1945,
    "end_year": 1975,
    "summary": "Cách mạng tháng Tám, Tuyên ngôn độc lập. Đất nước trải qua hai cuộc kháng chiến và bị chia cắt.",
    "agent_id": "agent_hien_dai_chia_cat",
    "color": "#006400",
    "notable_figures": [
      "Hồ Chí Minh",
      "Võ Nguyên Giáp"
    ],
    "key_events": [
      "Tuyên ngôn Độc lập (1945)",
      "Chiến thắng Điện Biên Phủ (1954)",
      "Hiệp định Genève (1954)",
      "Chiến dịch Hồ Chí Minh (1975)"
    ]
  },
  {
    "id": 27,
    "slug": "period_chxhcn_vn",
    "name": "Cộng hòa Xã hội Chủ nghĩa Việt Nam",
    "year_range": "1976 - nay",
    "start_year": 1976,
    "end_year": 2024,
    "summary": "Đất nước thống nhất, lấy tên là CHXHCN Việt Nam, thực hiện Đổi Mới (1986) và hội nhập quốc tế.",
    "agent_id": "agent_chxhcn_vn",
    "color": "#FF0000",
    "notable_figures": [
      "Lê Duẩn",
      "Nguyễn Văn Linh",
      "Võ Văn Kiệt"
    ],
    "key_events": [
      "Thống nhất đất nước về mặt nhà nước (1976)",
      "Chính sách Đổi Mới (1986)",
      "Gia nhập ASEAN (1995), WTO (2007)"
    ]
  }
]